{
  "Open Proposal" : {
    "transaction" : "Open Proposal",
    "sampleCount" : 1,
    "errorCount" : 1,
    "errorPct" : 100.0,
    "meanResTime" : 0.0,
    "medianResTime" : 0.0,
    "minResTime" : 0.0,
    "maxResTime" : 0.0,
    "pct1ResTime" : 0.0,
    "pct2ResTime" : 0.0,
    "pct3ResTime" : 0.0,
    "throughput" : "Infinity",
    "receivedKBytesPerSec" : "Infinity",
    "sentKBytesPerSec" : "NaN"
  },
  "Total" : {
    "transaction" : "Total",
    "sampleCount" : 3,
    "errorCount" : 2,
    "errorPct" : 66.666664,
    "meanResTime" : 2050.0,
    "medianResTime" : 0.0,
    "minResTime" : 0.0,
    "maxResTime" : 6150.0,
    "pct1ResTime" : 6150.0,
    "pct2ResTime" : 6150.0,
    "pct3ResTime" : 6150.0,
    "throughput" : 0.422237860661506,
    "receivedKBytesPerSec" : 22.458326002814918,
    "sentKBytesPerSec" : 0.0
  },
  "Login" : {
    "transaction" : "Login",
    "sampleCount" : 1,
    "errorCount" : 0,
    "errorPct" : 0.0,
    "meanResTime" : 6150.0,
    "medianResTime" : 6150.0,
    "minResTime" : 6150.0,
    "maxResTime" : 6150.0,
    "pct1ResTime" : 6150.0,
    "pct2ResTime" : 6150.0,
    "pct3ResTime" : 6150.0,
    "throughput" : 0.16260162601626016,
    "receivedKBytesPerSec" : 25.682482215447152,
    "sentKBytesPerSec" : 0.0
  },
  "Search Proposal" : {
    "transaction" : "Search Proposal",
    "sampleCount" : 1,
    "errorCount" : 1,
    "errorPct" : 100.0,
    "meanResTime" : 0.0,
    "medianResTime" : 0.0,
    "minResTime" : 0.0,
    "maxResTime" : 0.0,
    "pct1ResTime" : 0.0,
    "pct2ResTime" : 0.0,
    "pct3ResTime" : 0.0,
    "throughput" : "Infinity",
    "receivedKBytesPerSec" : "Infinity",
    "sentKBytesPerSec" : "NaN"
  }
}